advanced_yaml-0.5.0.dist-info/licenses/LICENSE
common/__init__.py
common/utils.py
yaql/__init__.py
yaql/cli.py
yaql/engine.py
yarl/__init__.py
yarl/cli.py
yasl/__init__.py
yasl/cache.py
yasl/cli.py
yasl/core.py
yasl/primitives.py
yasl/pydantic_types.py
yasl/validator_helpers.py
yasl/validators.py
yasl/sql/__init__.py
yasl/sql/types.py
yatl/__init__.py
yatl/cli.py
advanced_yaml-0.5.0.dist-info/METADATA
advanced_yaml-0.5.0.dist-info/WHEEL
advanced_yaml-0.5.0.dist-info/entry_points.txt
advanced_yaml-0.5.0.dist-info/top_level.txt
advanced_yaml-0.5.0.dist-info/RECORD
