Metadata-Version: 2.4
Name: advanced-yaml
Version: 0.5.0
Summary: A suite of tools to advance your usage of yaml.  YASL provides schema definition and verification.  YAQL let's you query your yalm as if it were a database.  YARL provides analysis and reporting.  And YATL allows you to transform yaml from one structure (schema) to another.
Requires-Python: >=3.12
License-File: LICENSE
Requires-Dist: astropy>=7.2.0
Requires-Dist: email-validator==2.3.0
Requires-Dist: markdown-it-py==4.0.0
Requires-Dist: pydantic==2.11.7
Requires-Dist: requests==2.32.5
Requires-Dist: ruamel-yaml==0.18.15
Requires-Dist: sqlmodel>=0.0.31
Requires-Dist: typing-extensions==4.15.0
Provides-Extra: dev
Requires-Dist: annotated-types==0.7.0; extra == "dev"
Requires-Dist: behave==1.3.2; extra == "dev"
Requires-Dist: build==1.3.0; extra == "dev"
Requires-Dist: certifi==2025.8.3; extra == "dev"
Requires-Dist: charset-normalizer==3.4.3; extra == "dev"
Requires-Dist: colorama==0.4.6; extra == "dev"
Requires-Dist: coverage==7.10.6; extra == "dev"
Requires-Dist: cucumber-expressions==18.0.1; extra == "dev"
Requires-Dist: cucumber-tag-expressions==6.2.0; extra == "dev"
Requires-Dist: dnspython==2.8.0; extra == "dev"
Requires-Dist: idna==3.10; extra == "dev"
Requires-Dist: iniconfig==2.1.0; extra == "dev"
Requires-Dist: mkdocs==1.6.1; extra == "dev"
Requires-Dist: mkdocs-material==9.6.22; extra == "dev"
Requires-Dist: packaging==25.0; extra == "dev"
Requires-Dist: parse==1.20.2; extra == "dev"
Requires-Dist: parse-type==0.6.6; extra == "dev"
Requires-Dist: pluggy==1.6.0; extra == "dev"
Requires-Dist: pydantic-core==2.33.2; extra == "dev"
Requires-Dist: pygments==2.19.2; extra == "dev"
Requires-Dist: pytest==8.4.1; extra == "dev"
Requires-Dist: pytest-cov==7.0.0; extra == "dev"
Requires-Dist: ruamel-yaml-clib==0.2.12; extra == "dev"
Requires-Dist: ruff==0.13.0; extra == "dev"
Requires-Dist: setuptools>=80.9.0; extra == "dev"
Requires-Dist: six==1.17.0; extra == "dev"
Requires-Dist: toml==0.10.2; extra == "dev"
Requires-Dist: typing-inspection==0.4.1; extra == "dev"
Requires-Dist: urllib3==2.6.0; extra == "dev"
Dynamic: license-file
